{"DataElement":{"publicId":"14599248","version":"1","preferredName":"Diffusion Weighted Imaging Performed Date","preferredDefinition":"Date that diffusion weighted imaging was performed.","longName":"DWI_PERF_DT","context":"CCTG","contextVersion":"1","DataElementConcept":{"publicId":"14599133","version":"1","preferredName":"Diffusion Weighted Imaging Performed","preferredDefinition":"A diffusion MRI technique in which diffusion-sensitizing gradients are applied to the imaging sequence.:Executed and carried through to completion.","longName":"4276400v1.00:2241241v1.00","context":"CCTG","contextVersion":"1","ObjectClass":{"publicId":"4276400","version":"1","preferredName":"Diffusion Weighted Imaging","preferredDefinition":"A diffusion MRI technique in which diffusion-sensitizing gradients are applied to the imaging sequence.","longName":"C111116","context":"NCIP","contextVersion":"1","Concepts":[{"longName":"Diffusion Weighted Imaging","conceptCode":"C111116","definition":"A diffusion MRI technique in which diffusion-sensitizing gradients are applied to the imaging sequence.","evsSource":"NCI_CONCEPT_CODE","primaryIndicator":"Yes","displayOrder":"0"}],"origin":"NCI Thesaurus","workflowStatus":"RELEASED","registrationStatus":"Application","id":"F7938F89-0762-E1D6-E040-BB89AD4305B1","latestVersionIndicator":"Yes","beginDate":"2014-04-21","endDate":null,"createdBy":"TAYLORT","dateCreated":"2014-04-21","modifiedBy":"ONEDATA","dateModified":"2014-04-21","changeDescription":null,"administrativeNotes":null,"unresolvedIssues":null,"deletedIndicator":"No"},"Property":{"publicId":"2241241","version":"1","preferredName":"Performed","preferredDefinition":"Performed; carried out.","longName":"C38000","context":"NCIP","contextVersion":"1","Concepts":[{"longName":"Performed","conceptCode":"C38000","definition":"Executed and carried through to completion.","evsSource":"NCI_CONCEPT_CODE","primaryIndicator":"Yes","displayOrder":"0"}],"origin":"NCI Thesaurus","workflowStatus":"RELEASED","registrationStatus":"Application","id":"F9FA7953-8839-043D-E034-0003BA3F9857","latestVersionIndicator":"Yes","beginDate":"2005-07-08","endDate":null,"createdBy":"SHIDED","dateCreated":"2005-07-08","modifiedBy":"ONEDATA","dateModified":"2005-07-08","changeDescription":null,"administrativeNotes":null,"unresolvedIssues":null,"deletedIndicator":"No"},"ConceptualDomain":{"publicId":"2008537","version":"1","preferredName":"Diagnosis","preferredDefinition":"the process of identifying a disease by the signs and symptoms (NCI Glossary).","longName":"DX","context":"CTEP","contextVersion":"2.31","origin":null,"workflowStatus":"RELEASED","registrationStatus":"Application","id":"B205508C-8324-69B0-E034-0003BA12F5E7","latestVersionIndicator":"Yes","beginDate":"2002-12-17","endDate":null,"createdBy":"MSUPLEY","dateCreated":"2002-12-17","modifiedBy":"SBR","dateModified":"2003-10-29","changeDescription":null,"administrativeNotes":null,"unresolvedIssues":null,"deletedIndicator":"No"},"origin":"CCTG: Canadian Cancer Trials Group","workflowStatus":"RELEASED","registrationStatus":"Application","id":"09BE134C-0659-3D7C-E063-731AD00AAFCE","latestVersionIndicator":"Yes","beginDate":"2023-11-09","endDate":null,"createdBy":"CLOHNES","dateCreated":"2023-11-09","modifiedBy":"CLOHNES","dateModified":"2024-01-10","changeDescription":null,"administrativeNotes":"1/10/23 Released for CCTG cjl;11/09/23 Created DEC for CCTG ticket number CADSR0003018 cjl.","unresolvedIssues":null,"deletedIndicator":"No"},"ValueDomain":{"publicId":"2018550","version":"1","preferredName":"Date","preferredDefinition":"The date on which an observation was made or an event occurred.","longName":"DT","context":"NCI Standards","contextVersion":"1","type":"Non-enumerated","dataType":"DATE","minLength":null,"maxLength":"8","minValue":null,"maxValue":null,"decimalPlace":null,"format":"MM/DD/YYYY","PermissibleValues":[],"ConceptualDomain":{"publicId":"2008561","version":"1","preferredName":"Occurrences","preferredDefinition":"dates, times, and durations.","longName":"OCURS","context":"CTEP","contextVersion":"2.31","origin":null,"workflowStatus":"RELEASED","registrationStatus":"Application","id":"B53BD1AB-090B-398B-E034-0003BA12F5E7","latestVersionIndicator":"Yes","beginDate":"2003-01-27","endDate":null,"createdBy":"MSUPLEY","dateCreated":"2003-01-27","modifiedBy":"SBR","dateModified":"2003-10-29","changeDescription":null,"administrativeNotes":null,"unresolvedIssues":null,"deletedIndicator":"No"},"RepresentationTerm":{"publicId":"2233081","version":"1","preferredName":"Date","preferredDefinition":"a particular day specified as the time something has, or will, happen.","longName":"C25164","context":"NCIP","contextVersion":"1","Concepts":[{"longName":"Date","conceptCode":"C25164","definition":"The particular day, month and year an event has happened or will happen.","evsSource":"NCI_CONCEPT_CODE","primaryIndicator":"Yes","displayOrder":"0"}],"origin":"NCI Thesaurus","workflowStatus":"RELEASED","registrationStatus":"Standard","id":"F90B5E56-BB15-0F45-E034-0003BA3F9857","latestVersionIndicator":"Yes","beginDate":"2005-06-09","endDate":null,"createdBy":"REEVESD","dateCreated":"2005-06-09","modifiedBy":"ONEDATA","dateModified":"2005-06-09","changeDescription":null,"administrativeNotes":null,"unresolvedIssues":null,"deletedIndicator":"No"},"origin":null,"workflowStatus":"RELEASED","registrationStatus":"Standard","id":"B54EF112-5457-674A-E034-0003BA12F5E7","latestVersionIndicator":"Yes","beginDate":"2003-01-28","endDate":null,"createdBy":"MSUPLEY","dateCreated":"2003-01-28","modifiedBy":"ZHWENDY","dateModified":"2023-12-12","changeDescription":"8/3/17 tt added Diagnosis CSI. 6/20/17 jk transferred to NCI Standards per confirmation by Brian Campbell as part of Round 5 finalization task, added reg status.","administrativeNotes":null,"unresolvedIssues":null,"deletedIndicator":"No"},"ClassificationSchemes":[],"AlternateNames":[{"name":"TU_TUYN_MRIDW","type":"OID, CCTG","context":"CCTG"},{"name":"TR_TRDAT_MRIDW_CR","type":"OID, CCTG","context":"CCTG"}],"ReferenceDocuments":[{"name":"PQT","type":"Preferred Question Text","description":"What date was the diffusion weighted imaging performed?","url":null,"context":"CCTG"},{"name":"CCTG_01","type":"Alternate Question Text","description":"If YES, Date MRI-DW performed:","url":null,"context":"CCTG"}],"origin":"CCTG: Canadian Cancer Trials Group","workflowStatus":"RELEASED","registrationStatus":"Application","id":"0A098D3B-63B9-1285-E063-731AD00A68E1","latestVersionIndicator":"Yes","beginDate":"2023-11-13","endDate":null,"createdBy":"CLOHNES","dateCreated":"2023-11-13","modifiedBy":"CLOHNES","dateModified":"2024-01-10","changeDescription":null,"administrativeNotes":"1/10/23 Released for CCTG cjl; 11/29/23 Added alt OID for CCTG ticket number CADSR0003123 cjl; 1/13/23 Created CDE for CCTG ticket number CADSR0003018 cjl.","unresolvedIssues":null,"deletedIndicator":"No"}}