{"DataElement":{"publicId":"2727659","version":"1","preferredName":"Visit Type Code","preferredDefinition":"The code that represents the period of the visit.","longName":"VST_TP_CD","context":"DCP","contextVersion":"1","DataElementConcept":{"publicId":"2182696","version":"1","preferredName":"Visit Report Month Type","preferredDefinition":"The number of months from the time of study entry until the date of a clinic visit being reported.\r\n","longName":"VST_REP_MON_TP","context":"DCP","contextVersion":"1","ObjectClass":{"publicId":"2181693","version":"1","preferredName":"Visit","preferredDefinition":"the act of going to see some person or place or thing for a short time.","longName":"Visit","context":"DCP","contextVersion":"1","Concepts":[{"longName":"Visit","conceptCode":"C25716","definition":"The act of going to see some person or place or thing; it can cover a short or long period but refers to a non-permanent arrangement.","evsSource":"NCI_CONCEPT_CODE","primaryIndicator":"Yes","displayOrder":"0"}],"origin":"NCI Thesaurus","workflowStatus":"RELEASED","registrationStatus":"Application","id":"D546EF0A-2F1B-35DC-E034-0003BA12F5E7","latestVersionIndicator":"Yes","beginDate":"2004-03-10","endDate":null,"createdBy":"MAESKEB","dateCreated":"2004-03-10","modifiedBy":"SBR","dateModified":"2005-03-29","changeDescription":null,"administrativeNotes":null,"unresolvedIssues":null,"deletedIndicator":"No"},"Property":{"publicId":"2182694","version":"1","preferredName":"Type","preferredDefinition":"Type; a subdivision of a particular kind of thing.","longName":"Type","context":"DCP","contextVersion":"1","Concepts":[{"longName":"Type","conceptCode":"C25284","definition":"Something distinguishable as an identifiable class based on common qualities.","evsSource":"NCI_CONCEPT_CODE","primaryIndicator":"Yes","displayOrder":"0"}],"origin":"NCI Thesaurus","workflowStatus":"RELEASED","registrationStatus":"Application","id":"D751EFE2-1F59-1EAF-E034-0003BA12F5E7","latestVersionIndicator":"Yes","beginDate":"2004-04-07","endDate":null,"createdBy":"MAESKEB","dateCreated":"2004-04-07","modifiedBy":"SBR","dateModified":"2005-09-08","changeDescription":null,"administrativeNotes":null,"unresolvedIssues":null,"deletedIndicator":"No"},"ConceptualDomain":{"publicId":"2008583","version":"1","preferredName":"Response","preferredDefinition":"a spoken or written statement that is made in reply to a question or request.","longName":"RESPONSE","context":"EDRN","contextVersion":"1","origin":null,"workflowStatus":"DRAFT NEW","registrationStatus":"Application","id":"CAAB9A16-A8FD-455E-E034-0003BA12F5E7","latestVersionIndicator":"Yes","beginDate":"2003-10-27","endDate":null,"createdBy":"CURTIST","dateCreated":"2003-10-27","modifiedBy":"SBR","dateModified":"2003-10-29","changeDescription":null,"administrativeNotes":null,"unresolvedIssues":null,"deletedIndicator":"No"},"origin":null,"workflowStatus":"RELEASED","registrationStatus":"Application","id":"D751EFE2-1F60-1EAF-E034-0003BA12F5E7","latestVersionIndicator":"Yes","beginDate":"2004-04-07","endDate":null,"createdBy":"MAESKEB","dateCreated":"2004-04-07","modifiedBy":"SBR","dateModified":"2016-06-06","changeDescription":null,"administrativeNotes":null,"unresolvedIssues":null,"deletedIndicator":"No"},"ValueDomain":{"publicId":"2727655","version":"1","preferredName":"Visit Type Code","preferredDefinition":"The code that represents the period of the visit.","longName":"VST_TP_CD","context":"DCP","contextVersion":"1","type":"Enumerated","dataType":"CHARACTER","minLength":"1","maxLength":"1","minValue":null,"maxValue":null,"decimalPlace":null,"PermissibleValues":[{"value":"7","valueDescription":"Follow-up","ValueMeaning":{"publicId":"2562220","version":"1","preferredName":"Follow-up","longName":"2562220","preferredDefinition":"Follow-up","context":"NCIP","contextVersion":"1","Concepts":[{"longName":"Follow-Up","conceptCode":"C16033","definition":"The process by which information about the health status of an individual is obtained after a study has officially closed; an activity that continues something that has already begun or that repeats something that has already been done.","evsSource":"NCI_CONCEPT_CODE","primaryIndicator":"Yes","displayOrder":"0"}],"origin":null,"workflowStatus":"RELEASED","registrationStatus":"Application","id":"2509CE87-C019-5C23-E044-0003BA3F9857","latestVersionIndicator":"Yes","beginDate":"2002-08-02","endDate":null,"createdBy":"SBREXT","dateCreated":"2002-08-02","modifiedBy":"KUMMEROA","dateModified":"2024-02-23","changeDescription":null,"administrativeNotes":null,"unresolvedIssues":null,"deletedIndicator":"No"},"origin":null,"id":"457FC700-1F22-6D85-E044-0003BA3F9857","beginDate":"2008-02-06","endDate":null,"createdBy":"MAESKEB","dateCreated":"2008-02-06","modifiedBy":"MAESKEB","dateModified":"2008-02-06","deletedIndicator":"No"},{"value":"6","valueDescription":"Month 6","ValueMeaning":{"publicId":"2574450","version":"1","preferredName":"Month 6","longName":"2574450","preferredDefinition":"Month 6","context":"NCIP","contextVersion":"1","Concepts":[],"origin":null,"workflowStatus":"RELEASED","registrationStatus":"Application","id":"2509CE87-EFDF-5C23-E044-0003BA3F9857","latestVersionIndicator":"Yes","beginDate":"2005-04-11","endDate":null,"createdBy":"SHIDED","dateCreated":"2005-04-11","modifiedBy":"SHIDED","dateModified":"2005-04-11","changeDescription":null,"administrativeNotes":null,"unresolvedIssues":null,"deletedIndicator":"No"},"origin":null,"id":"457FC700-1F37-6D85-E044-0003BA3F9857","beginDate":"2008-02-06","endDate":null,"createdBy":"MAESKEB","dateCreated":"2008-02-06","modifiedBy":"MAESKEB","dateModified":"2008-02-06","deletedIndicator":"No"},{"value":"5","valueDescription":"Month 5","ValueMeaning":{"publicId":"2727656","version":"1","preferredName":"Month 5","longName":"2727656","preferredDefinition":"Month 5","context":"NCIP","contextVersion":"1","Concepts":[],"origin":null,"workflowStatus":"RELEASED","registrationStatus":"Application","id":"457FC700-1F43-6D85-E044-0003BA3F9857","latestVersionIndicator":"Yes","beginDate":null,"endDate":null,"createdBy":"MAESKEB","dateCreated":"2008-02-06","modifiedBy":"SBR","dateModified":"2018-01-19","changeDescription":null,"administrativeNotes":null,"unresolvedIssues":null,"deletedIndicator":"No"},"origin":null,"id":"457FC700-1F5C-6D85-E044-0003BA3F9857","beginDate":"2008-02-06","endDate":null,"createdBy":"MAESKEB","dateCreated":"2008-02-06","modifiedBy":"MAESKEB","dateModified":"2008-02-06","deletedIndicator":"No"},{"value":"4","valueDescription":"Month 4","ValueMeaning":{"publicId":"2574798","version":"1","preferredName":"Month 4","longName":"2574798","preferredDefinition":"Month 4","context":"NCIP","contextVersion":"1","Concepts":[],"origin":null,"workflowStatus":"RELEASED","registrationStatus":"Application","id":"2509CE87-F13B-5C23-E044-0003BA3F9857","latestVersionIndicator":"Yes","beginDate":"2005-05-17","endDate":null,"createdBy":"MAESKEB","dateCreated":"2005-05-17","modifiedBy":"MAESKEB","dateModified":"2005-05-17","changeDescription":null,"administrativeNotes":null,"unresolvedIssues":null,"deletedIndicator":"No"},"origin":null,"id":"457FC700-1F71-6D85-E044-0003BA3F9857","beginDate":"2008-02-06","endDate":null,"createdBy":"MAESKEB","dateCreated":"2008-02-06","modifiedBy":"MAESKEB","dateModified":"2008-02-06","deletedIndicator":"No"},{"value":"3","valueDescription":"Month 3","ValueMeaning":{"publicId":"2574449","version":"1","preferredName":"Month 3","longName":"2574449","preferredDefinition":"Month 3","context":"NCIP","contextVersion":"1","Concepts":[],"origin":null,"workflowStatus":"RELEASED","registrationStatus":"Application","id":"2509CE87-EFDE-5C23-E044-0003BA3F9857","latestVersionIndicator":"Yes","beginDate":"2005-04-11","endDate":null,"createdBy":"SHIDED","dateCreated":"2005-04-11","modifiedBy":"SHIDED","dateModified":"2005-04-11","changeDescription":null,"administrativeNotes":null,"unresolvedIssues":null,"deletedIndicator":"No"},"origin":null,"id":"457FC700-1F86-6D85-E044-0003BA3F9857","beginDate":"2008-02-06","endDate":null,"createdBy":"MAESKEB","dateCreated":"2008-02-06","modifiedBy":"MAESKEB","dateModified":"2008-02-06","deletedIndicator":"No"},{"value":"2","valueDescription":"Month 2","ValueMeaning":{"publicId":"2574797","version":"1","preferredName":"Month 2","longName":"2574797","preferredDefinition":"Month 2","context":"NCIP","contextVersion":"1","Concepts":[],"origin":null,"workflowStatus":"RELEASED","registrationStatus":"Application","id":"2509CE87-F13A-5C23-E044-0003BA3F9857","latestVersionIndicator":"Yes","beginDate":"2005-05-17","endDate":null,"createdBy":"MAESKEB","dateCreated":"2005-05-17","modifiedBy":"MAESKEB","dateModified":"2005-05-17","changeDescription":null,"administrativeNotes":null,"unresolvedIssues":null,"deletedIndicator":"No"},"origin":null,"id":"457FC700-1F9B-6D85-E044-0003BA3F9857","beginDate":"2008-02-06","endDate":null,"createdBy":"MAESKEB","dateCreated":"2008-02-06","modifiedBy":"MAESKEB","dateModified":"2008-02-06","deletedIndicator":"No"},{"value":"1","valueDescription":"Month 1","ValueMeaning":{"publicId":"2574448","version":"1","preferredName":"Month 1","longName":"2574448","preferredDefinition":"Month 1","context":"NCIP","contextVersion":"1","Concepts":[],"origin":null,"workflowStatus":"RELEASED","registrationStatus":"Application","id":"2509CE87-EFDD-5C23-E044-0003BA3F9857","latestVersionIndicator":"Yes","beginDate":"2005-04-11","endDate":null,"createdBy":"SHIDED","dateCreated":"2005-04-11","modifiedBy":"SHIDED","dateModified":"2005-04-11","changeDescription":null,"administrativeNotes":null,"unresolvedIssues":null,"deletedIndicator":"No"},"origin":null,"id":"457FC700-1FB0-6D85-E044-0003BA3F9857","beginDate":"2008-02-06","endDate":null,"createdBy":"MAESKEB","dateCreated":"2008-02-06","modifiedBy":"MAESKEB","dateModified":"2008-02-06","deletedIndicator":"No"},{"value":"0","valueDescription":"Reg/Randomization","ValueMeaning":{"publicId":"2727657","version":"1","preferredName":"Reg/Randomization","longName":"2727657","preferredDefinition":"Registration/Randomization","context":"NCIP","contextVersion":"1","Concepts":[],"origin":null,"workflowStatus":"RELEASED","registrationStatus":"Application","id":"457FC700-1FBC-6D85-E044-0003BA3F9857","latestVersionIndicator":"Yes","beginDate":null,"endDate":null,"createdBy":"MAESKEB","dateCreated":"2008-02-06","modifiedBy":"SBR","dateModified":"2018-01-19","changeDescription":null,"administrativeNotes":null,"unresolvedIssues":null,"deletedIndicator":"No"},"origin":null,"id":"457FC700-1FD5-6D85-E044-0003BA3F9857","beginDate":"2008-02-06","endDate":null,"createdBy":"MAESKEB","dateCreated":"2008-02-06","modifiedBy":"MAESKEB","dateModified":"2008-02-06","deletedIndicator":"No"}],"ConceptualDomain":{"publicId":"2008528","version":"1","preferredName":"Protocol Administration","preferredDefinition":"the management of a research protocol and its case report forms.","longName":"PROT_ADM","context":"CTEP","contextVersion":"2.31","origin":null,"workflowStatus":"RELEASED","registrationStatus":"Application","id":"B1ECAD41-A932-34B1-E034-0003BA12F5E7","latestVersionIndicator":"Yes","beginDate":"2002-12-16","endDate":null,"createdBy":"MSUPLEY","dateCreated":"2002-12-16","modifiedBy":"SBR","dateModified":"2003-10-29","changeDescription":null,"administrativeNotes":null,"unresolvedIssues":null,"deletedIndicator":"No"},"RepresentationTerm":{"publicId":"2543234","version":"1","preferredName":"Type Code","preferredDefinition":"Type; a subdivision of a particular kind of thing.:A system of numbered categories for representation of data.","longName":"C25284:C25162","context":"NCIP","contextVersion":"1","Concepts":[{"longName":"Type","conceptCode":"C25284","definition":"Something distinguishable as an identifiable class based on common qualities.","evsSource":"NCI_CONCEPT_CODE","primaryIndicator":"No","displayOrder":"1"},{"longName":"Code","conceptCode":"C25162","definition":"A symbol or combination of symbols which is assigned to the members of a collection.","evsSource":"NCI_CONCEPT_CODE","primaryIndicator":"Yes","displayOrder":"0"}],"origin":null,"workflowStatus":"RELEASED","registrationStatus":"Application","id":"22741A04-0C77-5EC9-E044-0003BA3F9857","latestVersionIndicator":"Yes","beginDate":"2006-11-17","endDate":null,"createdBy":"COOPERM","dateCreated":"2006-11-17","modifiedBy":"ONEDATA","dateModified":"2006-11-17","changeDescription":null,"administrativeNotes":null,"unresolvedIssues":null,"deletedIndicator":"No"},"origin":null,"workflowStatus":"RELEASED","registrationStatus":"Application","id":"457FC6EB-8C0F-69D3-E044-0003BA3F9857","latestVersionIndicator":"Yes","beginDate":"2008-02-06","endDate":null,"createdBy":"MAESKEB","dateCreated":"2008-02-06","modifiedBy":"SBR","dateModified":"2008-12-08","changeDescription":null,"administrativeNotes":null,"unresolvedIssues":null,"deletedIndicator":"No"},"ClassificationSchemes":[{"publicId":"2194255","version":"1","longName":"Type of Condition","context":"DCP","ClassificationSchemeItems":[{"publicId":"2812155","version":"1","longName":"Sporadic Colorectal Neoplasia - Atrovastatin","context":"DCP"}]}],"AlternateNames":[],"ReferenceDocuments":[{"name":"Visit Type","type":"Preferred Question Text","description":"Visit Type","url":null,"context":"DCP"}],"origin":null,"workflowStatus":"RELEASED","registrationStatus":"Qualified","id":"457FCC92-3BC0-6EBA-E044-0003BA3F9857","latestVersionIndicator":"Yes","beginDate":"2008-02-06","endDate":null,"createdBy":"MAESKEB","dateCreated":"2008-02-06","modifiedBy":"MAESKEB","dateModified":"2008-02-12","changeDescription":null,"administrativeNotes":null,"unresolvedIssues":null,"deletedIndicator":"No"}}