{"DataElement":{"publicId":"3626590","version":"1","preferredName":"Reporting Evaluation Period ANBL12P1 Code","preferredDefinition":"a numbered category system for representation of the ANBL12P1 reporting evaluation period for a patient assessment.","longName":"ANBL12P1ReportingPeriod","context":"COG","contextVersion":"1","DataElementConcept":{"publicId":"2190169","version":"1","preferredName":"Reporting Evaluation Period","preferredDefinition":"information related to the reporting evaluation period.","longName":"REP_EVAL_PD","context":"CTEP","contextVersion":"2.31","ObjectClass":{"publicId":"2206724","version":"1","preferredName":"Reporting Evaluation","preferredDefinition":"The act of providing a short account.:Evaluation; the act of placing value on something.","longName":"C25651:C25214","context":"NCIP","contextVersion":"1","Concepts":[{"longName":"Reporting","conceptCode":"C25651","definition":"The act of providing a short account.","evsSource":"NCI_CONCEPT_CODE","primaryIndicator":"No","displayOrder":"1"},{"longName":"Evaluation","conceptCode":"C25214","definition":"Systematic, objective appraisal of the significance, effectiveness, and impact of activities or condition according to specified objectives and criteria.","evsSource":"NCI_CONCEPT_CODE","primaryIndicator":"Yes","displayOrder":"0"}],"origin":null,"workflowStatus":"RELEASED","registrationStatus":"Application","id":"F37D0429-01F6-6787-E034-0003BA3F9857","latestVersionIndicator":"Yes","beginDate":"2005-03-29","endDate":null,"createdBy":"SBR","dateCreated":"2005-03-29","modifiedBy":"ONEDATA","dateModified":"2005-03-29","changeDescription":null,"administrativeNotes":null,"unresolvedIssues":null,"deletedIndicator":"No"},"Property":{"publicId":"2177446","version":"1","preferredName":"Period","preferredDefinition":"Period; an amount of time.","longName":"Period","context":"CTEP","contextVersion":"2.31","Concepts":[{"longName":"Period","conceptCode":"C25616","definition":"An interval of time.","evsSource":"NCI_CONCEPT_CODE","primaryIndicator":"Yes","displayOrder":"0"}],"origin":"NCI Thesaurus","workflowStatus":"RELEASED","registrationStatus":"Application","id":"AE29A78C-5258-3A05-E034-0003BA12F5E7","latestVersionIndicator":"Yes","beginDate":"2002-10-29","endDate":null,"createdBy":"SBREXT","dateCreated":"2002-10-29","modifiedBy":"SBR","dateModified":"2005-04-06","changeDescription":null,"administrativeNotes":null,"unresolvedIssues":null,"deletedIndicator":"No"},"ConceptualDomain":{"publicId":"2008551","version":"1","preferredName":"Assessments","preferredDefinition":"evaluations of the patient and the patient's disease.","longName":"ASSESS","context":"CTEP","contextVersion":"2.31","origin":null,"workflowStatus":"RELEASED","registrationStatus":"Application","id":"B22DA727-6718-5A2D-E034-0003BA12F5E7","latestVersionIndicator":"Yes","beginDate":"2002-12-19","endDate":null,"createdBy":"MSUPLEY","dateCreated":"2002-12-19","modifiedBy":"SBR","dateModified":"2003-10-29","changeDescription":null,"administrativeNotes":null,"unresolvedIssues":null,"deletedIndicator":"No"},"origin":null,"workflowStatus":"RELEASED","registrationStatus":"Application","id":"E6F61A36-549E-3204-E034-0003BA3F9857","latestVersionIndicator":"Yes","beginDate":"2004-10-21","endDate":null,"createdBy":"CAMPBELB","dateCreated":"2004-10-21","modifiedBy":"SBR","dateModified":"2016-06-06","changeDescription":null,"administrativeNotes":null,"unresolvedIssues":null,"deletedIndicator":"No"},"ValueDomain":{"publicId":"3626582","version":"1","preferredName":"Reporting Evaluation Period ANBL12P1 Code","preferredDefinition":"a numbered category system for representation of the ANBL12P1 reporting evaluation period for a patient assessment.","longName":"ANBL12P1ReportingPeriod","context":"COG","contextVersion":"1","type":"Enumerated","dataType":"CHARACTER","minLength":"1","maxLength":"10","minValue":null,"maxValue":null,"decimalPlace":null,"PermissibleValues":[{"value":"3","valueDescription":"RP 3 - Induction Cycle 5","ValueMeaning":{"publicId":"3626585","version":"1","preferredName":"RP 3 - Induction Cycle 5","longName":"3626585","preferredDefinition":"RP 3 - Induction Cycle 5","context":"NCIP","contextVersion":"1","Concepts":[],"origin":null,"workflowStatus":"RELEASED","registrationStatus":"Application","id":"CE8F08B0-F28B-24D7-E040-BB89AD433142","latestVersionIndicator":"Yes","beginDate":"2012-11-15","endDate":null,"createdBy":"WONGW","dateCreated":"2012-11-15","modifiedBy":"SBR","dateModified":"2018-01-19","changeDescription":null,"administrativeNotes":null,"unresolvedIssues":null,"deletedIndicator":"No"},"origin":null,"id":"CE8F08B0-F2A4-24D7-E040-BB89AD433142","beginDate":"2012-11-15","endDate":null,"createdBy":"WONGW","dateCreated":"2012-11-15","modifiedBy":"ONEDATA","dateModified":"2012-11-15","deletedIndicator":"No"},{"value":"16","valueDescription":"Follow Up 11 (10 yrs)","ValueMeaning":{"publicId":"3626720","version":"1","preferredName":"Follow Up 11 (10 yrs)","longName":"3626720","preferredDefinition":"Follow Up 11 (10 yrs)","context":"NCIP","contextVersion":"1","Concepts":[],"origin":null,"workflowStatus":"RELEASED","registrationStatus":"Application","id":"CEA1A4C7-CFE5-9206-E040-BB89AD432E71","latestVersionIndicator":"Yes","beginDate":"2012-11-16","endDate":null,"createdBy":"WONGW","dateCreated":"2012-11-16","modifiedBy":"SBR","dateModified":"2018-01-19","changeDescription":null,"administrativeNotes":null,"unresolvedIssues":null,"deletedIndicator":"No"},"origin":null,"id":"CEA1A4C7-CFFE-9206-E040-BB89AD432E71","beginDate":"2012-11-16","endDate":null,"createdBy":"WONGW","dateCreated":"2012-11-16","modifiedBy":"ONEDATA","dateModified":"2012-11-16","deletedIndicator":"No"},{"value":"15","valueDescription":"Follow Up 10 (9 yrs)","ValueMeaning":{"publicId":"3626721","version":"1","preferredName":"Follow Up 10 (9 yrs)","longName":"3626721","preferredDefinition":"Follow Up 10 (9 yrs)","context":"NCIP","contextVersion":"1","Concepts":[],"origin":null,"workflowStatus":"RELEASED","registrationStatus":"Application","id":"CEA1A4C7-D008-9206-E040-BB89AD432E71","latestVersionIndicator":"Yes","beginDate":"2012-11-16","endDate":null,"createdBy":"WONGW","dateCreated":"2012-11-16","modifiedBy":"SBR","dateModified":"2018-01-19","changeDescription":null,"administrativeNotes":null,"unresolvedIssues":null,"deletedIndicator":"No"},"origin":null,"id":"CEA1A4C7-D021-9206-E040-BB89AD432E71","beginDate":"2012-11-16","endDate":null,"createdBy":"WONGW","dateCreated":"2012-11-16","modifiedBy":"ONEDATA","dateModified":"2012-11-16","deletedIndicator":"No"},{"value":"14","valueDescription":"Follow Up 9 (8 yrs)","ValueMeaning":{"publicId":"3626722","version":"1","preferredName":"Follow Up 9 (8 yrs)","longName":"3626722","preferredDefinition":"Follow Up 9 (8 yrs)","context":"NCIP","contextVersion":"1","Concepts":[],"origin":null,"workflowStatus":"RELEASED","registrationStatus":"Application","id":"CEA1A4C7-D02B-9206-E040-BB89AD432E71","latestVersionIndicator":"Yes","beginDate":"2012-11-16","endDate":null,"createdBy":"WONGW","dateCreated":"2012-11-16","modifiedBy":"SBR","dateModified":"2018-01-19","changeDescription":null,"administrativeNotes":null,"unresolvedIssues":null,"deletedIndicator":"No"},"origin":null,"id":"CEA1A4C7-D044-9206-E040-BB89AD432E71","beginDate":"2012-11-16","endDate":null,"createdBy":"WONGW","dateCreated":"2012-11-16","modifiedBy":"ONEDATA","dateModified":"2012-11-16","deletedIndicator":"No"},{"value":"13","valueDescription":"Follow Up 8 (7 yrs)","ValueMeaning":{"publicId":"3626723","version":"1","preferredName":"Follow Up 8 (7 yrs)","longName":"3626723","preferredDefinition":"Follow Up 8 (7 yrs)","context":"NCIP","contextVersion":"1","Concepts":[],"origin":null,"workflowStatus":"RELEASED","registrationStatus":"Application","id":"CEA1A4C7-D04E-9206-E040-BB89AD432E71","latestVersionIndicator":"Yes","beginDate":"2012-11-16","endDate":null,"createdBy":"WONGW","dateCreated":"2012-11-16","modifiedBy":"SBR","dateModified":"2018-01-19","changeDescription":null,"administrativeNotes":null,"unresolvedIssues":null,"deletedIndicator":"No"},"origin":null,"id":"CEA1A4C7-D067-9206-E040-BB89AD432E71","beginDate":"2012-11-16","endDate":null,"createdBy":"WONGW","dateCreated":"2012-11-16","modifiedBy":"ONEDATA","dateModified":"2012-11-16","deletedIndicator":"No"},{"value":"12","valueDescription":"Follow Up 7 (6 yrs)","ValueMeaning":{"publicId":"3626724","version":"1","preferredName":"Follow Up 7 (6 yrs)","longName":"3626724","preferredDefinition":"Follow Up 7 (6 yrs)","context":"NCIP","contextVersion":"1","Concepts":[],"origin":null,"workflowStatus":"RELEASED","registrationStatus":"Application","id":"CEA1A4C7-D071-9206-E040-BB89AD432E71","latestVersionIndicator":"Yes","beginDate":"2012-11-16","endDate":null,"createdBy":"WONGW","dateCreated":"2012-11-16","modifiedBy":"SBR","dateModified":"2018-01-19","changeDescription":null,"administrativeNotes":null,"unresolvedIssues":null,"deletedIndicator":"No"},"origin":null,"id":"CEA1A4C7-D08A-9206-E040-BB89AD432E71","beginDate":"2012-11-16","endDate":null,"createdBy":"WONGW","dateCreated":"2012-11-16","modifiedBy":"ONEDATA","dateModified":"2012-11-16","deletedIndicator":"No"},{"value":"11","valueDescription":"Follow Up 6 (5 yrs)","ValueMeaning":{"publicId":"3544466","version":"1","preferredName":"Follow Up 6 (5 yrs)","longName":"3544466","preferredDefinition":"Follow Up 6 (5 yrs)","context":"NCIP","contextVersion":"1","Concepts":[],"origin":null,"workflowStatus":"RELEASED","registrationStatus":"Application","id":"C69C14AA-CE40-F300-E040-BB89AD433FD6","latestVersionIndicator":"Yes","beginDate":"2012-08-06","endDate":null,"createdBy":"SHIDED","dateCreated":"2012-08-06","modifiedBy":"SBR","dateModified":"2018-01-19","changeDescription":null,"administrativeNotes":null,"unresolvedIssues":null,"deletedIndicator":"No"},"origin":null,"id":"CEA1A4C7-D09E-9206-E040-BB89AD432E71","beginDate":"2012-11-16","endDate":null,"createdBy":"WONGW","dateCreated":"2012-11-16","modifiedBy":"ONEDATA","dateModified":"2012-11-16","deletedIndicator":"No"},{"value":"10","valueDescription":"Follow Up 5 (4 yrs)","ValueMeaning":{"publicId":"3544467","version":"1","preferredName":"Follow Up 5 (4 yrs)","longName":"3544467","preferredDefinition":"Follow Up 5 (4 yrs)","context":"NCIP","contextVersion":"1","Concepts":[],"origin":null,"workflowStatus":"RELEASED","registrationStatus":"Application","id":"C69C14AA-CE63-F300-E040-BB89AD433FD6","latestVersionIndicator":"Yes","beginDate":"2012-08-06","endDate":null,"createdBy":"SHIDED","dateCreated":"2012-08-06","modifiedBy":"SBR","dateModified":"2018-01-19","changeDescription":null,"administrativeNotes":null,"unresolvedIssues":null,"deletedIndicator":"No"},"origin":null,"id":"CEA1A4C7-D0B2-9206-E040-BB89AD432E71","beginDate":"2012-11-16","endDate":null,"createdBy":"WONGW","dateCreated":"2012-11-16","modifiedBy":"ONEDATA","dateModified":"2012-11-16","deletedIndicator":"No"},{"value":"9","valueDescription":"Follow Up 4 (3 yrs)","ValueMeaning":{"publicId":"3544468","version":"1","preferredName":"Follow Up 4 (3 yrs)","longName":"3544468","preferredDefinition":"Follow Up 4 (3 yrs)","context":"NCIP","contextVersion":"1","Concepts":[],"origin":null,"workflowStatus":"RELEASED","registrationStatus":"Application","id":"C69C14AA-CE86-F300-E040-BB89AD433FD6","latestVersionIndicator":"Yes","beginDate":"2012-08-06","endDate":null,"createdBy":"SHIDED","dateCreated":"2012-08-06","modifiedBy":"SBR","dateModified":"2018-01-19","changeDescription":null,"administrativeNotes":null,"unresolvedIssues":null,"deletedIndicator":"No"},"origin":null,"id":"CEA1A4C7-D0C6-9206-E040-BB89AD432E71","beginDate":"2012-11-16","endDate":null,"createdBy":"WONGW","dateCreated":"2012-11-16","modifiedBy":"ONEDATA","dateModified":"2012-11-16","deletedIndicator":"No"},{"value":"8","valueDescription":"Follow Up 3 (2 yrs)","ValueMeaning":{"publicId":"3544469","version":"1","preferredName":"Follow Up 3 (2 yrs)","longName":"3544469","preferredDefinition":"Follow Up 3 (2 yrs)","context":"NCIP","contextVersion":"1","Concepts":[],"origin":null,"workflowStatus":"RELEASED","registrationStatus":"Application","id":"C69C14AA-CEA9-F300-E040-BB89AD433FD6","latestVersionIndicator":"Yes","beginDate":"2012-08-06","endDate":null,"createdBy":"SHIDED","dateCreated":"2012-08-06","modifiedBy":"SBR","dateModified":"2018-01-19","changeDescription":null,"administrativeNotes":null,"unresolvedIssues":null,"deletedIndicator":"No"},"origin":null,"id":"CEA1A4C7-D0DA-9206-E040-BB89AD432E71","beginDate":"2012-11-16","endDate":null,"createdBy":"WONGW","dateCreated":"2012-11-16","modifiedBy":"ONEDATA","dateModified":"2012-11-16","deletedIndicator":"No"},{"value":"7","valueDescription":"Follow Up 2 (1 yr)","ValueMeaning":{"publicId":"3544470","version":"1","preferredName":"Follow Up 2 (1 yr)","longName":"3544470","preferredDefinition":"Follow Up 2 (1 yr)","context":"NCIP","contextVersion":"1","Concepts":[],"origin":null,"workflowStatus":"RELEASED","registrationStatus":"Application","id":"C69C14AA-CECC-F300-E040-BB89AD433FD6","latestVersionIndicator":"Yes","beginDate":"2012-08-06","endDate":null,"createdBy":"SHIDED","dateCreated":"2012-08-06","modifiedBy":"SBR","dateModified":"2018-01-19","changeDescription":null,"administrativeNotes":null,"unresolvedIssues":null,"deletedIndicator":"No"},"origin":null,"id":"CEA1A4C7-D0EE-9206-E040-BB89AD432E71","beginDate":"2012-11-16","endDate":null,"createdBy":"WONGW","dateCreated":"2012-11-16","modifiedBy":"ONEDATA","dateModified":"2012-11-16","deletedIndicator":"No"},{"value":"6","valueDescription":"Follow Up 1 (6 mo)","ValueMeaning":{"publicId":"3544471","version":"1","preferredName":"Follow Up 1 (6 mo)","longName":"3544471","preferredDefinition":"Follow Up 1 (6 mo)","context":"NCIP","contextVersion":"1","Concepts":[],"origin":null,"workflowStatus":"RELEASED","registrationStatus":"Application","id":"C69C14AA-CEEF-F300-E040-BB89AD433FD6","latestVersionIndicator":"Yes","beginDate":"2012-08-06","endDate":null,"createdBy":"SHIDED","dateCreated":"2012-08-06","modifiedBy":"SBR","dateModified":"2018-01-19","changeDescription":null,"administrativeNotes":null,"unresolvedIssues":null,"deletedIndicator":"No"},"origin":null,"id":"CEA1A4C7-D102-9206-E040-BB89AD432E71","beginDate":"2012-11-16","endDate":null,"createdBy":"WONGW","dateCreated":"2012-11-16","modifiedBy":"ONEDATA","dateModified":"2012-11-16","deletedIndicator":"No"},{"value":"5","valueDescription":"RP5 -  Consolidation 2, Day 29  - end of Consolidation","ValueMeaning":{"publicId":"3626726","version":"1","preferredName":"RP5 -  Consolidation 2, Day 29  - end of Consolidation","longName":"3626726","preferredDefinition":"RP5 -  Consolidation 2, Day 29  - end of Consolidation","context":"NCIP","contextVersion":"1","Concepts":[],"origin":null,"workflowStatus":"RELEASED","registrationStatus":"Application","id":"CEA1A4C7-D12F-9206-E040-BB89AD432E71","latestVersionIndicator":"Yes","beginDate":"2012-11-16","endDate":null,"createdBy":"WONGW","dateCreated":"2012-11-16","modifiedBy":"SBR","dateModified":"2018-01-19","changeDescription":null,"administrativeNotes":null,"unresolvedIssues":null,"deletedIndicator":"No"},"origin":null,"id":"CEA1A4C7-D148-9206-E040-BB89AD432E71","beginDate":"2012-11-15","endDate":null,"createdBy":"WONGW","dateCreated":"2012-11-16","modifiedBy":"ONEDATA","dateModified":"2012-11-16","deletedIndicator":"No"},{"value":"1","valueDescription":"RP 1 - Induction Cycle 1 & 2","ValueMeaning":{"publicId":"3626727","version":"1","preferredName":"RP 1 - Induction Cycle 1 & 2","longName":"3626727","preferredDefinition":"RP 1 - Induction Cycle 1 & 2","context":"NCIP","contextVersion":"1","Concepts":[],"origin":null,"workflowStatus":"RELEASED","registrationStatus":"Application","id":"CEA20070-5589-7687-E040-BB89AD434A17","latestVersionIndicator":"Yes","beginDate":"2012-11-16","endDate":null,"createdBy":"WONGW","dateCreated":"2012-11-16","modifiedBy":"SBR","dateModified":"2018-01-19","changeDescription":null,"administrativeNotes":null,"unresolvedIssues":null,"deletedIndicator":"No"},"origin":null,"id":"CEA20070-55A2-7687-E040-BB89AD434A17","beginDate":"2012-11-15","endDate":null,"createdBy":"WONGW","dateCreated":"2012-11-16","modifiedBy":"ONEDATA","dateModified":"2012-11-16","deletedIndicator":"No"},{"value":"2","valueDescription":"RP 2 - Induction Cycle 3 & 4","ValueMeaning":{"publicId":"3626728","version":"1","preferredName":"RP 2 - Induction Cycle 3 & 4","longName":"3626728","preferredDefinition":"RP 2 - Induction Cycle 3 & 4","context":"NCIP","contextVersion":"1","Concepts":[],"origin":null,"workflowStatus":"RELEASED","registrationStatus":"Application","id":"CEA20070-55AC-7687-E040-BB89AD434A17","latestVersionIndicator":"Yes","beginDate":"2012-11-16","endDate":null,"createdBy":"WONGW","dateCreated":"2012-11-16","modifiedBy":"SBR","dateModified":"2018-01-19","changeDescription":null,"administrativeNotes":null,"unresolvedIssues":null,"deletedIndicator":"No"},"origin":null,"id":"CEA20070-55C5-7687-E040-BB89AD434A17","beginDate":"2012-11-15","endDate":null,"createdBy":"WONGW","dateCreated":"2012-11-16","modifiedBy":"ONEDATA","dateModified":"2012-11-16","deletedIndicator":"No"},{"value":"4","valueDescription":"RP 4 - Consolidation 1, Day -7 (pre-transplant)  - Day 28 (post-transplant)","ValueMeaning":{"publicId":"3682551","version":"1","preferredName":"RP 4 - Consolidation 1, Day -7 (pre-transplant)  - Day 28 (post-transplant)","longName":"3682551","preferredDefinition":"RP 4 - Consolidation 1, Day -7 (pre-transplant)  - Day 28 (post-transplant)","context":"NCIP","contextVersion":"1","Concepts":[],"origin":null,"workflowStatus":"RELEASED","registrationStatus":"Application","id":"D52A41C3-9230-0D3C-E040-BB89AD4320E5","latestVersionIndicator":"Yes","beginDate":"2013-02-07","endDate":null,"createdBy":"WONGW","dateCreated":"2013-02-07","modifiedBy":"SBR","dateModified":"2018-01-19","changeDescription":null,"administrativeNotes":null,"unresolvedIssues":null,"deletedIndicator":"No"},"origin":null,"id":"D52A41C3-9249-0D3C-E040-BB89AD4320E5","beginDate":"2012-11-15","endDate":null,"createdBy":"WONGW","dateCreated":"2013-02-07","modifiedBy":"ONEDATA","dateModified":"2013-02-07","deletedIndicator":"No"},{"value":"0","valueDescription":"Baseline","ValueMeaning":{"publicId":"2561148","version":"1","preferredName":"Baseline","longName":"2561148","preferredDefinition":"A starting point to which things may be compared.","context":"NCIP","contextVersion":"1","Concepts":[{"longName":"Baseline","conceptCode":"C25213","definition":"A starting point to which things may be compared.","evsSource":"NCI_CONCEPT_CODE","primaryIndicator":"Yes","displayOrder":"0"}],"origin":null,"workflowStatus":"RELEASED","registrationStatus":"Application","id":"2509CE87-BBE9-5C23-E044-0003BA3F9857","latestVersionIndicator":"Yes","beginDate":"2002-05-14","endDate":null,"createdBy":"CVALMONT","dateCreated":"2002-05-14","modifiedBy":"KUMMEROA","dateModified":"2023-03-29","changeDescription":"Updated concept definition to match current NCIt. mc 4/13/17","administrativeNotes":null,"unresolvedIssues":null,"deletedIndicator":"No"},"origin":null,"id":"D5275F80-AB94-46F5-E040-BB89AD430765","beginDate":"2013-02-07","endDate":null,"createdBy":"WONGW","dateCreated":"2013-02-07","modifiedBy":"ONEDATA","dateModified":"2013-02-07","deletedIndicator":"No"}],"ConceptualDomain":{"publicId":"2008551","version":"1","preferredName":"Assessments","preferredDefinition":"evaluations of the patient and the patient's disease.","longName":"ASSESS","context":"CTEP","contextVersion":"2.31","origin":null,"workflowStatus":"RELEASED","registrationStatus":"Application","id":"B22DA727-6718-5A2D-E034-0003BA12F5E7","latestVersionIndicator":"Yes","beginDate":"2002-12-19","endDate":null,"createdBy":"MSUPLEY","dateCreated":"2002-12-19","modifiedBy":"SBR","dateModified":"2003-10-29","changeDescription":null,"administrativeNotes":null,"unresolvedIssues":null,"deletedIndicator":"No"},"RepresentationTerm":{"publicId":"2261841","version":"1","preferredName":"Code","preferredDefinition":"A system of numbered categories for representation of data.","longName":"C25162","context":"NCIP","contextVersion":"1","Concepts":[{"longName":"Code","conceptCode":"C25162","definition":"A symbol or combination of symbols which is assigned to the members of a collection.","evsSource":"NCI_CONCEPT_CODE","primaryIndicator":"Yes","displayOrder":"0"}],"origin":"NCI Thesaurus","workflowStatus":"RELEASED","registrationStatus":"Standard","id":"FBB87F7A-6427-1AFC-E034-0003BA3F9857","latestVersionIndicator":"Yes","beginDate":"2005-07-13","endDate":null,"createdBy":"MAESKEB","dateCreated":"2005-07-13","modifiedBy":"SBR","dateModified":"2005-09-08","changeDescription":null,"administrativeNotes":null,"unresolvedIssues":null,"deletedIndicator":"No"},"origin":"COG CRF:Children's Oncology Group Case Report Form","workflowStatus":"RELEASED","registrationStatus":"Application","id":"CE8F08B0-F231-24D7-E040-BB89AD433142","latestVersionIndicator":"Yes","beginDate":"2012-11-15","endDate":null,"createdBy":"WONGW","dateCreated":"2012-11-15","modifiedBy":"SBR","dateModified":"2014-01-02","changeDescription":" Changed from CTEP to COG for by script Thu Jan 2 10:00:57 EST 2014","administrativeNotes":null,"unresolvedIssues":null,"deletedIndicator":"No"},"ClassificationSchemes":[{"publicId":"2961451","version":"1","longName":"Children's Oncology Group (COG)","context":"COG","ClassificationSchemeItems":[{"publicId":"2961452","version":"1","longName":"Statistics and Data Center","context":"COG"}]}],"AlternateNames":[],"ReferenceDocuments":[{"name":"ANBL12P1 Reporting Period:","type":"Preferred Question Text","description":"ANBL12P1 Reporting Period:","url":null,"context":"CTEP"}],"origin":"COG CRF:Children's Oncology Group Case Report Form","workflowStatus":"RELEASED","registrationStatus":"Application","id":"CE901836-E817-140B-E040-BB89AD4340F8","latestVersionIndicator":"Yes","beginDate":"2012-11-15","endDate":null,"createdBy":"WONGW","dateCreated":"2012-11-15","modifiedBy":"SBR","dateModified":"2014-01-02","changeDescription":" Changed from CTEP to COG for by script Thu Jan 2 10:00:57 EST 2014","administrativeNotes":null,"unresolvedIssues":null,"deletedIndicator":"No"}}