{"DataElement":{"publicId":"5334834","version":"1","preferredName":"Vendor serial number","preferredDefinition":"The serial number of the device.","longName":"2681266v1.2:5332758v1.0","context":"AHRQ","contextVersion":"1","DataElementConcept":{"publicId":"2681266","version":"1.2","preferredName":"Equipment Serial Number","preferredDefinition":"One or more characters used to identify a manufacturer-provided serial number of an automated device that created the observations  used for cancer-related research, diagnosis or therapy.","longName":"EQUIP_SERIAL_NBR","context":"NCIP","contextVersion":"1","ObjectClass":{"publicId":"2236764","version":"1","preferredName":"Diagnostic, Therapeutic, and Research Equipment","preferredDefinition":"An object needed to perform a diagnostic, therapeutic or research activity.","longName":"C19238","context":"NCIP","contextVersion":"1","Concepts":[{"longName":"Diagnostic, Therapeutic, or Research Equipment","conceptCode":"C19238","definition":"A manufactured object that is used to perform diagnostic, therapeutic or research activities.","evsSource":"NCI_CONCEPT_CODE","primaryIndicator":"Yes","displayOrder":"0"}],"origin":"NCI Thesaurus","workflowStatus":"RELEASED","registrationStatus":"Application","id":"F9FC77A4-29E7-502D-E034-0003BA3F9857","latestVersionIndicator":"Yes","beginDate":"2005-06-20","endDate":null,"createdBy":"UMLLOADER_MAGE","dateCreated":"2005-06-20","modifiedBy":"SBREXT","dateModified":"2007-11-07","changeDescription":null,"administrativeNotes":null,"unresolvedIssues":null,"deletedIndicator":"No"},"Property":{"publicId":"2933470","version":"1","preferredName":"Device Observer Serial Number","preferredDefinition":"No value exists.","longName":"C69253","context":"NCIP","contextVersion":"1","Concepts":[{"longName":"Device Observer Serial Number","conceptCode":"C69253","definition":"The serial number of an automated observation device.","evsSource":"NCI_CONCEPT_CODE","primaryIndicator":"Yes","displayOrder":"0"}],"origin":"NCI Thesaurus","workflowStatus":"RELEASED","registrationStatus":"Application","id":"71610818-4F3B-2451-E040-BB89AD436DE8","latestVersionIndicator":"Yes","beginDate":"2009-08-17","endDate":null,"createdBy":"CHILLIJ","dateCreated":"2009-08-17","modifiedBy":"ONEDATA","dateModified":"2009-08-17","changeDescription":null,"administrativeNotes":null,"unresolvedIssues":null,"deletedIndicator":"No"},"ConceptualDomain":{"publicId":"2233241","version":"1","preferredName":"Medical Imaging","preferredDefinition":"Events, people, materials and activities uniquely defined by medical imaging.  ","longName":"MEDICAL IMAGING","context":"CIP","contextVersion":"2.31","origin":"DICOM:Digital Imaging and Communications in Medicine","workflowStatus":"RELEASED","registrationStatus":"Application","id":"F96173D7-A9B4-3CBB-E034-0003BA3F9857","latestVersionIndicator":"Yes","beginDate":"2005-06-12","endDate":null,"createdBy":"REEVESD","dateCreated":"2005-06-12","modifiedBy":"SBREXT","dateModified":"2006-09-13","changeDescription":null,"administrativeNotes":null,"unresolvedIssues":null,"deletedIndicator":"No"},"origin":"DICOM:Digital Imaging and Communications in Medicine","workflowStatus":"RELEASED","registrationStatus":"Application","id":"71610818-4F4C-2451-E040-BB89AD436DE8","latestVersionIndicator":"Yes","beginDate":"2009-08-17","endDate":null,"createdBy":"CHILLIJ","dateCreated":"2009-08-17","modifiedBy":"REEVESD","dateModified":"2016-06-29","changeDescription":"8/17/09 property chg to serial number only; remove identifer, per VCDE caBIG review.  3/30/09 released.  3/9/09 versioned for different OC concept per direction of EVS. 10/5/08 - released post NCIA Interim Rpt Changes;  10/1/07  Updated with DICOM term CUI.  9/12/07  DEC created to support DICOM task utilizing IE &amp; DICOM Attribute terms.","administrativeNotes":null,"unresolvedIssues":null,"deletedIndicator":"No"},"ValueDomain":{"publicId":"5332758","version":"1","preferredName":"Encapsulated Data Text","preferredDefinition":"A data type comprised of encapsulated data in the form of text._The words of something written.","longName":"5332758v1.0","context":"ONC SDC Project","contextVersion":"1","type":"Non-enumerated","dataType":"HL7EDv3","minLength":null,"maxLength":"200","minValue":null,"maxValue":null,"decimalPlace":null,"PermissibleValues":[],"ConceptualDomain":{"publicId":"2008556","version":"1","preferredName":"Assessment Results","preferredDefinition":"the results of evaluations of the patient and the patient's disease.","longName":"ASSESS_RESULTS","context":"CTEP","contextVersion":"2.31","origin":null,"workflowStatus":"RELEASED","registrationStatus":"Application","id":"B2D08DE9-38BB-7208-E034-0003BA12F5E7","latestVersionIndicator":"Yes","beginDate":"2002-12-27","endDate":null,"createdBy":"MSUPLEY","dateCreated":"2002-12-27","modifiedBy":"SBR","dateModified":"2003-10-29","changeDescription":null,"administrativeNotes":null,"unresolvedIssues":null,"deletedIndicator":"No"},"RepresentationTerm":{"publicId":"5377011","version":"1","preferredName":"Encapsulated Data Text Data Type Text","preferredDefinition":"A data type comprised of encapsulated data in the form of text.:The words of something written.","longName":"C95652:C25704","context":"NCIP","contextVersion":"1","Concepts":[{"longName":"Encapsulated Data Text Data Type","conceptCode":"C95652","definition":"A data type comprised of encapsulated data in the form of text.","evsSource":"NCI_CONCEPT_CODE","primaryIndicator":"No","displayOrder":"1"},{"longName":"Text","conceptCode":"C25704","definition":"The words of something written.","evsSource":"NCI_CONCEPT_CODE","primaryIndicator":"Yes","displayOrder":"0"}],"origin":null,"workflowStatus":"RELEASED","registrationStatus":"Application","id":"3930B303-FA6F-91DB-E050-BB89AD4355F0","latestVersionIndicator":"Yes","beginDate":"2016-08-03","endDate":null,"createdBy":"REEVESD","dateCreated":"2016-08-03","modifiedBy":"ONEDATA","dateModified":"2016-08-03","changeDescription":null,"administrativeNotes":null,"unresolvedIssues":null,"deletedIndicator":"No"},"origin":"AHRQ:AHRQ Common Formats","workflowStatus":"RELEASED","registrationStatus":"Application","id":"36733FF8-57E3-DFF1-E050-BB89AD436C8E","latestVersionIndicator":"Yes","beginDate":"2016-06-29","endDate":null,"createdBy":"REEVESD","dateCreated":"2016-06-29","modifiedBy":"REEVESD","dateModified":"2017-02-10","changeDescription":null,"administrativeNotes":null,"unresolvedIssues":null,"deletedIndicator":"No"},"ClassificationSchemes":[{"publicId":"4382693","version":"1","longName":"AHRQ Common Formats","context":"AHRQ","ClassificationSchemeItems":[{"publicId":"5406432","version":"1","longName":"DEVICE 1.2","context":"AHRQ"}]}],"AlternateNames":[{"name":"DE174","type":"AHRQ Identifier","context":"ONC SDC Project"}],"ReferenceDocuments":[{"name":"What is the serial number?","type":"Preferred Question Text","description":"What is the serial number?","url":null,"context":"ONC SDC Project"},{"name":"DEVICE|74725-3","type":"AHRQ Form","description":"Device or Medical/Surgical Supply, including Heath Information Technology (HIT)|Patient safety event report - hospital: device or medical AndOr surgical supply, including health information technology (HIT) - version 1.2 [AHRQ]","url":"https://www.psoppc.org/psoppc_web/DLMS/downloadDocument?groupId&#61;97&amp;pageName&#61;common%20formats%20version%201.2%20technical%20specifications","context":"ONC SDC Project"}],"origin":"AHRQ:AHRQ Common Formats","workflowStatus":"RELEASED","registrationStatus":"Application","id":"36D07468-2DE0-4AA7-E050-BB89AD435C2C","latestVersionIndicator":"Yes","beginDate":"2010-03-31","endDate":null,"createdBy":"REEVESD","dateCreated":"2016-07-04","modifiedBy":"DWARZEL","dateModified":"2017-02-28","changeDescription":"Block Edit to add Device 1.2 CSI. Curated as part of AHRQ Common Format CDE creation.1.15.2017.dmr","administrativeNotes":null,"unresolvedIssues":null,"deletedIndicator":"No"}}