{"DataElement":{"publicId":"62586","version":"5","preferredName":"Person Address City Name","preferredDefinition":"the city or township for the address.  This can be for either a person or organization.","longName":"PERSON_ADDR_CIT_NAME","context":"CTEP","contextVersion":"2.31","DataElementConcept":{"publicId":"2014826","version":"1","preferredName":"Person Address","preferredDefinition":"the address or postal information for a person.","longName":"PERSON_ADDR","context":"CTEP","contextVersion":"2.31","ObjectClass":{"publicId":"2236731","version":"1","preferredName":"Person","preferredDefinition":"A human being.","longName":"C25190","context":"NCIP","contextVersion":"1","Concepts":[{"longName":"Person","conceptCode":"C25190","definition":"A human being.","evsSource":"NCI_CONCEPT_CODE","primaryIndicator":"Yes","displayOrder":"0"}],"origin":"NCI Thesaurus","workflowStatus":"RELEASED","registrationStatus":"Application","id":"F9FC6DF7-66EB-4CAB-E034-0003BA3F9857","latestVersionIndicator":"Yes","beginDate":"2005-06-20","endDate":null,"createdBy":"UMLLOADER_MAGE","dateCreated":"2005-06-20","modifiedBy":"SBREXT","dateModified":"2007-11-07","changeDescription":null,"administrativeNotes":null,"unresolvedIssues":null,"deletedIndicator":"No"},"Property":{"publicId":"2177663","version":"1","preferredName":"Address","preferredDefinition":"The location at which an organization or person can be reached. (from American Heritage Dictionary)","longName":"Address","context":"CTEP","contextVersion":"2.31","Concepts":[{"longName":"Address","conceptCode":"C25407","definition":"A standardized representation of the location of a person, business, building, or organization.","evsSource":"NCI_CONCEPT_CODE","primaryIndicator":"Yes","displayOrder":"0"}],"origin":"NCI Thesaurus","workflowStatus":"RELEASED","registrationStatus":"Application","id":"AE29A78C-516B-3A05-E034-0003BA12F5E7","latestVersionIndicator":"Yes","beginDate":"2002-10-29","endDate":null,"createdBy":"SBREXT","dateCreated":"2002-10-29","modifiedBy":"SBR","dateModified":"2005-09-08","changeDescription":null,"administrativeNotes":null,"unresolvedIssues":null,"deletedIndicator":"No"},"ConceptualDomain":{"publicId":"2008543","version":"1","preferredName":"Geographic Locations","preferredDefinition":"all components of an address, including building number, street name and type, city, state, postal code, and country.","longName":"GEO_LCTNS","context":"CTEP","contextVersion":"2.31","origin":null,"workflowStatus":"RELEASED","registrationStatus":"Application","id":"B227ED46-D8B2-4A76-E034-0003BA12F5E7","latestVersionIndicator":"Yes","beginDate":"2002-12-19","endDate":null,"createdBy":"MSUPLEY","dateCreated":"2002-12-19","modifiedBy":"SBR","dateModified":"2003-10-29","changeDescription":null,"administrativeNotes":null,"unresolvedIssues":null,"deletedIndicator":"No"},"origin":null,"workflowStatus":"RELEASED","registrationStatus":"Application","id":"C03C1340-34CD-239F-E034-0003BA12F5E7","latestVersionIndicator":"Yes","beginDate":"2003-06-16","endDate":null,"createdBy":"MWHITE","dateCreated":"2003-06-16","modifiedBy":"SBR","dateModified":"2016-06-06","changeDescription":null,"administrativeNotes":null,"unresolvedIssues":null,"deletedIndicator":"No"},"ValueDomain":{"publicId":"2019047","version":"1","preferredName":"Person Address City Name","preferredDefinition":"the name of a city for the address or poatal information of a person.","longName":"PERSON_ADDR_CIT_NAME","context":"CTEP","contextVersion":"2.31","type":"Non-enumerated","dataType":"CHARACTER","minLength":null,"maxLength":"50","minValue":null,"maxValue":null,"decimalPlace":null,"PermissibleValues":[],"ConceptualDomain":{"publicId":"2008543","version":"1","preferredName":"Geographic Locations","preferredDefinition":"all components of an address, including building number, street name and type, city, state, postal code, and country.","longName":"GEO_LCTNS","context":"CTEP","contextVersion":"2.31","origin":null,"workflowStatus":"RELEASED","registrationStatus":"Application","id":"B227ED46-D8B2-4A76-E034-0003BA12F5E7","latestVersionIndicator":"Yes","beginDate":"2002-12-19","endDate":null,"createdBy":"MSUPLEY","dateCreated":"2002-12-19","modifiedBy":"SBR","dateModified":"2003-10-29","changeDescription":null,"administrativeNotes":null,"unresolvedIssues":null,"deletedIndicator":"No"},"RepresentationTerm":{"publicId":"2208042","version":"1","preferredName":"City Name","preferredDefinition":"City; a large and densely populated urban area.:Personal names, given or surname, as cultural characteristics, as ethnological or religious patterns, as indications of the geographic distribution of families and inbreeding, etc. Analysis of isonymy, the quality of having the same or similar names, is useful in the study of population genetics. NAMES is used also for the history of names or name changes of corporate bodies, such as medical societies, universities, hospitals, government agencies, etc.","longName":"C25160:C25191","context":"NCIP","contextVersion":"1","Concepts":[{"longName":"City","conceptCode":"C25160","definition":"A large and densely populated urban area; a city specified in an address.","evsSource":"NCI_CONCEPT_CODE","primaryIndicator":"No","displayOrder":"1"},{"longName":"Person Name","conceptCode":"C25191","definition":"A word or group of words indicating the identity of a person usually consisting of a first (personal) name and a last (family) name with an optional middle name. In some cultural traditions the family name comes first.","evsSource":"NCI_CONCEPT_CODE","primaryIndicator":"Yes","displayOrder":"0"}],"origin":"NCI Thesaurus","workflowStatus":"RELEASED","registrationStatus":"Application","id":"F37D0429-3A5E-6787-E034-0003BA3F9857","latestVersionIndicator":"Yes","beginDate":"2005-03-29","endDate":null,"createdBy":"SBR","dateCreated":"2005-03-29","modifiedBy":"ONEDATA","dateModified":"2005-03-29","changeDescription":null,"administrativeNotes":null,"unresolvedIssues":null,"deletedIndicator":"No"},"origin":null,"workflowStatus":"RELEASED","registrationStatus":"Application","id":"C03C20F3-846D-2373-E034-0003BA12F5E7","latestVersionIndicator":"Yes","beginDate":"2003-06-16","endDate":null,"createdBy":"MWHITE","dateCreated":"2003-06-16","modifiedBy":"SBREXT","dateModified":"2007-11-07","changeDescription":null,"administrativeNotes":null,"unresolvedIssues":null,"deletedIndicator":"No"},"ClassificationSchemes":[{"publicId":"2008587","version":"2","longName":"Type of Disease","context":"CTEP","ClassificationSchemeItems":[{"publicId":"2811907","version":"1","longName":"Bladder","context":"CTEP"}]},{"publicId":"2008589","version":"2","longName":"Type of Category","context":"CTEP","ClassificationSchemeItems":[{"publicId":"2811960","version":"1","longName":"Patient Demographics","context":"CTEP"}]},{"publicId":"2183535","version":"1","longName":"Clinical Trial Mgmt Systems","context":"NCIP","ClassificationSchemeItems":[{"publicId":"2812625","version":"1","longName":"CTMS C3D Adopter Sites","context":"NCIP"},{"publicId":"2812831","version":"1","longName":"Oregon Health & Sciences University","context":"NCIP"},{"publicId":"2812832","version":"1","longName":"OHSU_288","context":"NCIP"}]},{"publicId":"2190530","version":"1","longName":"Demonstration Applications","context":"NCIP","ClassificationSchemeItems":[{"publicId":"2812347","version":"1","longName":"Firebird","context":"NCIP"}]},{"publicId":"2724612","version":"0.53","longName":"Clinical Trials Object Data System (CTODS)","context":"NCIP","ClassificationSchemeItems":[{"publicId":"10000404","version":"1","longName":"gov.nih.nci.ctom.domain","context":"NCIP"}]},{"publicId":"2857180","version":"1","longName":"Type of Category","context":"NIDCR","ClassificationSchemeItems":[{"publicId":"2812086","version":"1","longName":"Restorative","context":"NIDCR"}]},{"publicId":"2857182","version":"1","longName":"Protocol Forms","context":"NIDCR","ClassificationSchemeItems":[{"publicId":"2812039","version":"1","longName":"PEARL","context":"NIDCR"}]},{"publicId":"2931931","version":"1","longName":"Iloprost Trial","context":"SPOREs","ClassificationSchemeItems":[{"publicId":"2931952","version":"1","longName":"Iloprost 12079","context":"SPOREs"}]},{"publicId":"2961451","version":"1","longName":"Children's Oncology Group (COG)","context":"COG","ClassificationSchemeItems":[{"publicId":"2961452","version":"1","longName":"Statistics and Data Center","context":"COG"}]}],"AlternateNames":[{"name":"PERSON_ADDR_CIT_NAME","type":"USED_BY","context":"SPOREs"},{"name":"PERSON_ADDR_CIT_NAME","type":"USED_BY","context":"NIDCR"},{"name":"PERSON_ADDR_CIT_NAME","type":"USED_BY","context":"NCIP"},{"name":"PERSON_ADDR_CIT_NAME","type":"USED_BY","context":"CIP"},{"name":"PERSON_ADDR_CIT_NAME","type":"USED_BY","context":"CCR"},{"name":"caBIG","type":"USED_BY","context":"NCIP"},{"name":"gov.nih.nci.ctom.domain.Person.city","type":"UML Qualified Attr","context":"NCIP"},{"name":"Person:city","type":"UML Class:UML Attr","context":"NCIP"},{"name":"ADDRESS_CITY","type":"COG Form Element","context":"CTEP"}],"ReferenceDocuments":[{"name":"City","type":"Preferred Question Text","description":"City","url":null,"context":"CTEP"},{"name":"CRF Text","type":"Alternate Question Text","description":"Address, City","url":null,"context":"CTEP"},{"name":"City/Town","type":"Alternate Question Text","description":"City/Town","url":null,"context":"NIDCR"}],"origin":null,"workflowStatus":"RELEASED","registrationStatus":"Qualified","id":"C03C08B8-29CF-2383-E034-0003BA12F5E7","latestVersionIndicator":"Yes","beginDate":"2003-06-16","endDate":null,"createdBy":"MWHITE","dateCreated":"2003-06-16","modifiedBy":"REEVESD","dateModified":"2011-04-05","changeDescription":"ISO 11175 Compliance","administrativeNotes":null,"unresolvedIssues":null,"deletedIndicator":"No"}}