{"DataElement":{"publicId":"7873425","version":"1","preferredName":"Gynecological Examination Vulvar Irritation Score 4 Point Scale","preferredDefinition":"The extent of vulvar irritation assessed by a gynecological examination, using a 4-point scale.","longName":"GYNEX_VULIRRTATN_SCL","context":"NCIP","contextVersion":"1","DataElementConcept":{"publicId":"7849166","version":"1","preferredName":"Gynecological Examination Presence of Vaginal Vestibular Irritation Assessment","preferredDefinition":"Physical examination pertaining to the female reproductive system._A question about whether an individual has vaginal vestibular irritation._The final result of a determination of the value, significance, or extent of.","longName":"8031118v1.0:8037875v1.0","context":"NCIP","contextVersion":"1","ObjectClass":{"publicId":"8031118","version":"1","preferredName":"Gynecological Examination","preferredDefinition":"Physical examination pertaining to the female reproductive system.","longName":"C137854","context":"NCIP","contextVersion":"1","Concepts":[{"longName":"Gynecological Examination","conceptCode":"C137854","definition":"Physical examination pertaining to the female reproductive system.","evsSource":"NCI_CONCEPT_CODE","primaryIndicator":"Yes","displayOrder":"0"}],"origin":"NCI Thesaurus","workflowStatus":"RELEASED","registrationStatus":"Application","id":"D78A66FE-35DF-0D16-E053-4EBD850A58FF","latestVersionIndicator":"Yes","beginDate":"2022-02-08","endDate":null,"createdBy":"TSESU","dateCreated":"2022-02-08","modifiedBy":"ONEDATA","dateModified":"2022-02-08","changeDescription":null,"administrativeNotes":null,"unresolvedIssues":null,"deletedIndicator":"No"},"Property":{"publicId":"8037875","version":"1","preferredName":"Presence of Vaginal Vestibular Irritation Assessment","preferredDefinition":"A question about whether an individual has vaginal vestibular irritation.:The final result of a determination of the value, significance, or extent of.","longName":"C185365:C25217","context":"NCIP","contextVersion":"1","Concepts":[{"longName":"Presence of Vaginal Vestibular Irritation","conceptCode":"C185365","definition":"A question about whether an individual has vaginal vestibular irritation.","evsSource":"NCI_CONCEPT_CODE","primaryIndicator":"No","displayOrder":"1"},{"longName":"Assessment","conceptCode":"C25217","definition":"The final result of a determination of the value, significance, or extent of.","evsSource":"NCI_CONCEPT_CODE","primaryIndicator":"Yes","displayOrder":"0"}],"origin":null,"workflowStatus":"RELEASED","registrationStatus":"Application","id":"D7ACCFBB-4030-7A5F-E053-4EBD850A8D88","latestVersionIndicator":"Yes","beginDate":"2022-02-10","endDate":null,"createdBy":"TSESU","dateCreated":"2022-02-10","modifiedBy":"ONEDATA","dateModified":"2022-02-10","changeDescription":null,"administrativeNotes":null,"unresolvedIssues":null,"deletedIndicator":"No"},"ConceptualDomain":{"publicId":"2524082","version":"1","preferredName":"Person Measure/Instrument Testing","preferredDefinition":"Process and results associated with self-reported measures and instruments, surveys, other tools","longName":"MEASURE/INSTRUMENT TESTING","context":"CCR","contextVersion":"1","origin":"CCR:Center for Cancer Research","workflowStatus":"RELEASED","registrationStatus":"Application","id":"1E838B40-6636-0A25-E044-0003BA3F9857","latestVersionIndicator":"Yes","beginDate":"2006-09-28","endDate":null,"createdBy":"REEVESD","dateCreated":"2006-09-28","modifiedBy":"REEVESD","dateModified":"2008-11-19","changeDescription":null,"administrativeNotes":null,"unresolvedIssues":null,"deletedIndicator":"No"},"origin":null,"workflowStatus":"RELEASED","registrationStatus":"Application","id":"D296AE3B-2A7D-0D86-E053-4EBD850ADEE8","latestVersionIndicator":"Yes","beginDate":"2021-12-07","endDate":null,"createdBy":"TSESU","dateCreated":"2021-12-07","modifiedBy":"TSESU","dateModified":"2022-03-30","changeDescription":null,"administrativeNotes":null,"unresolvedIssues":null,"deletedIndicator":"No"},"ValueDomain":{"publicId":"8035916","version":"1","preferredName":"Vulvar Irritation Scale","preferredDefinition":"An ordered reference standard used to measure incremental changes.","longName":"8035916v1.0","context":"NCIP","contextVersion":"1","type":"Enumerated","dataType":"NUMBER","minLength":null,"maxLength":"2","minValue":"0","maxValue":"99","decimalPlace":"0","PermissibleValues":[{"value":"99","valueDescription":"NOT ASSESSED","ValueMeaning":{"publicId":"2559594","version":"1","preferredName":"NOT ASSESSED","longName":"2559594","preferredDefinition":"Indicates that an assessment was not performed.","context":"NCIP","contextVersion":"1","Concepts":[{"longName":"Not Assessed","conceptCode":"C139527","definition":"Indicates that an assessment was not performed.","evsSource":"NCI_CONCEPT_CODE","primaryIndicator":"Yes","displayOrder":"0"}],"origin":null,"workflowStatus":"RELEASED","registrationStatus":"Application","id":"2509CE87-B5D7-5C23-E044-0003BA3F9857","latestVersionIndicator":"Yes","beginDate":"2002-02-13","endDate":null,"createdBy":"SBR","dateCreated":"2002-02-13","modifiedBy":"MMADDINENI","dateModified":"2024-02-20","changeDescription":null,"administrativeNotes":null,"unresolvedIssues":null,"deletedIndicator":"No"},"origin":null,"id":"D7AC0D3A-AEAB-171F-E053-4EBD850A0915","beginDate":"2022-02-10","endDate":null,"createdBy":"TSESU","dateCreated":"2022-02-10","modifiedBy":"ONEDATA","dateModified":"2022-02-10","deletedIndicator":"No"},{"value":"0","valueDescription":"Absent","ValueMeaning":{"publicId":"3204360","version":"1","preferredName":"Absent","longName":"3204360","preferredDefinition":"Not existing in a specified place at a specified time.","context":"NCIP","contextVersion":"1","Concepts":[{"longName":"Absent","conceptCode":"C48190","definition":"Not existing in a specified place at a specified time.","evsSource":"NCI_CONCEPT_CODE","primaryIndicator":"Yes","displayOrder":"0"}],"origin":null,"workflowStatus":"RELEASED","registrationStatus":"Application","id":"9E9F26F2-9C11-947B-E040-BB89AD434D7C","latestVersionIndicator":"Yes","beginDate":"2011-03-16","endDate":null,"createdBy":"LUY","dateCreated":"2011-03-16","modifiedBy":"CLOHNES","dateModified":"2023-11-14","changeDescription":"Concept annotation added for UPitt/TCGA.  Ylu, 01/30/2015.","administrativeNotes":null,"unresolvedIssues":null,"deletedIndicator":"No"},"origin":null,"id":"D7AC0D3A-AEB5-171F-E053-4EBD850A0915","beginDate":"2022-02-10","endDate":null,"createdBy":"TSESU","dateCreated":"2022-02-10","modifiedBy":"ONEDATA","dateModified":"2022-02-10","deletedIndicator":"No"},{"value":"3","valueDescription":"Severe Erythema (greater than or equal to 25%)","ValueMeaning":{"publicId":"5505489","version":"1","preferredName":"Severe Erythema (greater than or equal to 25%)","longName":"5505489","preferredDefinition":"Intensely bad or unpleasant in degree, quality or extent.: Red discoloration of the skin caused by infectious agents, inflammation, drug hypersensitivity, or underlying disease.","context":"NCIP","contextVersion":"1","Concepts":[{"longName":"Severe","conceptCode":"C70667","definition":"Intensely bad or unpleasant in degree, quality or extent.","evsSource":"NCI_CONCEPT_CODE","primaryIndicator":"No","displayOrder":"1"},{"longName":"Erythema","conceptCode":"C26901","definition":"Red discoloration of the skin caused by infectious agents, inflammation, drug hypersensitivity, or underlying disease.","evsSource":"NCI_CONCEPT_CODE","primaryIndicator":"Yes","displayOrder":"0"}],"origin":null,"workflowStatus":"RELEASED","registrationStatus":"Application","id":"3E234CD4-CCAE-58BB-E053-F662850AFF8B","latestVersionIndicator":"Yes","beginDate":"2016-10-05","endDate":null,"createdBy":"HARTLEYG","dateCreated":"2016-10-05","modifiedBy":"SBR","dateModified":"2018-01-19","changeDescription":null,"administrativeNotes":null,"unresolvedIssues":null,"deletedIndicator":"No"},"origin":null,"id":"D7AC0D3A-AEC1-171F-E053-4EBD850A0915","beginDate":"2022-02-10","endDate":null,"createdBy":"TSESU","dateCreated":"2022-02-10","modifiedBy":"ONEDATA","dateModified":"2022-02-10","deletedIndicator":"No"},{"value":"2","valueDescription":"Moderate Erythema","ValueMeaning":{"publicId":"8035917","version":"1","preferredName":"Moderate Erythema","longName":"8035917","preferredDefinition":"The quality of being within reasonable or average limits; not excessive or extreme.: Red discoloration of the skin caused by infectious agents, inflammation, drug hypersensitivity, or underlying disease.","context":"NCIP","contextVersion":"1","Concepts":[{"longName":"Moderate","conceptCode":"C61376","definition":"The quality of being within reasonable or average limits; not excessive or extreme.","evsSource":"NCI_CONCEPT_CODE","primaryIndicator":"No","displayOrder":"1"},{"longName":"Erythema","conceptCode":"C26901","definition":"Red discoloration of the skin caused by infectious agents, inflammation, drug hypersensitivity, or underlying disease.","evsSource":"NCI_CONCEPT_CODE","primaryIndicator":"Yes","displayOrder":"0"}],"origin":null,"workflowStatus":"RELEASED","registrationStatus":"Application","id":"D7AC0D3A-AECF-171F-E053-4EBD850A0915","latestVersionIndicator":"Yes","beginDate":"2022-02-10","endDate":null,"createdBy":"TSESU","dateCreated":"2022-02-10","modifiedBy":"ONEDATA","dateModified":"2022-02-10","changeDescription":null,"administrativeNotes":null,"unresolvedIssues":null,"deletedIndicator":"No"},"origin":null,"id":"D7AC0D3A-AEEA-171F-E053-4EBD850A0915","beginDate":"2022-02-10","endDate":null,"createdBy":"TSESU","dateCreated":"2022-02-10","modifiedBy":"ONEDATA","dateModified":"2022-02-10","deletedIndicator":"No"},{"value":"1","valueDescription":"Mild Erythema","ValueMeaning":{"publicId":"8035918","version":"1","preferredName":"Mild Erythema","longName":"8035918","preferredDefinition":"Gentle or temperate in nature or degree.: Red discoloration of the skin caused by infectious agents, inflammation, drug hypersensitivity, or underlying disease.","context":"NCIP","contextVersion":"1","Concepts":[{"longName":"Mild","conceptCode":"C70666","definition":"Gentle or temperate in nature or degree.","evsSource":"NCI_CONCEPT_CODE","primaryIndicator":"No","displayOrder":"1"},{"longName":"Erythema","conceptCode":"C26901","definition":"Red discoloration of the skin caused by infectious agents, inflammation, drug hypersensitivity, or underlying disease.","evsSource":"NCI_CONCEPT_CODE","primaryIndicator":"Yes","displayOrder":"0"}],"origin":null,"workflowStatus":"RELEASED","registrationStatus":"Application","id":"D7AC0D3A-AEF7-171F-E053-4EBD850A0915","latestVersionIndicator":"Yes","beginDate":"2022-02-10","endDate":null,"createdBy":"TSESU","dateCreated":"2022-02-10","modifiedBy":"ONEDATA","dateModified":"2022-02-10","changeDescription":null,"administrativeNotes":null,"unresolvedIssues":null,"deletedIndicator":"No"},"origin":null,"id":"D7AC0D3A-AF12-171F-E053-4EBD850A0915","beginDate":"2022-02-10","endDate":null,"createdBy":"TSESU","dateCreated":"2022-02-10","modifiedBy":"ONEDATA","dateModified":"2022-02-10","deletedIndicator":"No"}],"ConceptualDomain":{"publicId":"2524082","version":"1","preferredName":"Person Measure/Instrument Testing","preferredDefinition":"Process and results associated with self-reported measures and instruments, surveys, other tools","longName":"MEASURE/INSTRUMENT TESTING","context":"CCR","contextVersion":"1","origin":"CCR:Center for Cancer Research","workflowStatus":"RELEASED","registrationStatus":"Application","id":"1E838B40-6636-0A25-E044-0003BA3F9857","latestVersionIndicator":"Yes","beginDate":"2006-09-28","endDate":null,"createdBy":"REEVESD","dateCreated":"2006-09-28","modifiedBy":"REEVESD","dateModified":"2008-11-19","changeDescription":null,"administrativeNotes":null,"unresolvedIssues":null,"deletedIndicator":"No"},"RepresentationTerm":{"publicId":"2452834","version":"1","preferredName":"Scale","preferredDefinition":"an ordered reference standard.","longName":"C25664","context":"NCIP","contextVersion":"1","Concepts":[{"longName":"Scale","conceptCode":"C25664","definition":"An ordered reference standard used to measure incremental changes.","evsSource":"NCI_CONCEPT_CODE","primaryIndicator":"Yes","displayOrder":"0"}],"origin":"NCI Thesaurus","workflowStatus":"RELEASED","registrationStatus":"Standard","id":"0D51E8D8-69DD-387C-E044-0003BA3F9857","latestVersionIndicator":"Yes","beginDate":"2006-02-24","endDate":null,"createdBy":"CAMPBELB","dateCreated":"2006-02-24","modifiedBy":"ONEDATA","dateModified":"2006-02-24","changeDescription":null,"administrativeNotes":null,"unresolvedIssues":null,"deletedIndicator":"No"},"origin":null,"workflowStatus":"RELEASED","registrationStatus":"Application","id":"D7AC0D3A-AE93-171F-E053-4EBD850A0915","latestVersionIndicator":"Yes","beginDate":"2022-02-10","endDate":null,"createdBy":"TSESU","dateCreated":"2022-02-10","modifiedBy":"TSESU","dateModified":"2022-06-24","changeDescription":null,"administrativeNotes":null,"unresolvedIssues":null,"deletedIndicator":"No"},"ClassificationSchemes":[],"AlternateNames":[],"ReferenceDocuments":[{"name":"Vulvar Irritation","type":"Preferred Question Text","description":"Vulvar Irritation","url":null,"context":"NCIP"}],"origin":null,"workflowStatus":"RELEASED","registrationStatus":"Application","id":"D2BE2BB3-158B-696F-E053-4EBD850A1229","latestVersionIndicator":"Yes","beginDate":"2021-12-09","endDate":null,"createdBy":"TSESU","dateCreated":"2021-12-09","modifiedBy":"TSESU","dateModified":"2022-07-07","changeDescription":"Created for Alliance per K. Laumann.","administrativeNotes":null,"unresolvedIssues":null,"deletedIndicator":"No"}}